<?xml version="1.0" encoding="ISO-8859-1" ?>
<!DOCTYPE tiles-definitions PUBLIC
       "-//Apache Software Foundation//DTD Tiles Configuration 2.0//EN"
       "http://tiles.apache.org/dtds/tiles-config_2_0.dtd">

<tiles-definitions>
	<definition name="baseLayout" template="/layouts/base.jsp">
		<put-attribute name="htmlExtHeader" value="/tiles/defaultHtmlExtHeader.jsp" />
		<put-attribute name="header" value="/tiles/header.jsp" />
		<put-attribute name="footer" value="/tiles/footer.jsp" />
	</definition>

	<definition name="baseLayoutWithMenu" template="/layouts/base_menu.jsp" extends="baseLayout">
		<put-attribute name="header" value="/tiles/headermenu.jsp" />
	</definition>

	<!--  Login and Security -->
	<definition name="loginPage" extends="baseLayout">
		<put-attribute name="body" value="/tiles/login/login.jsp" />
	</definition>

	<definition name="homePage" extends="baseLayoutWithMenu">
		<put-attribute name="body" value="/tiles/home/home.jsp" />
	</definition>
	
	<definition name="accessdeniedPage" extends="baseLayout">
		<put-attribute name="body" value="/tiles/login/accessdenied.jsp" />
	</definition>
	
	<!-- Employee tiles definition -->
	<definition name="listEmployeesPage" extends="baseLayoutWithMenu">
		<put-attribute name="body" value="/tiles/employee/list.jsp" />
	</definition>
		
	<definition name="editEmployeePage" extends="baseLayoutWithMenu">
		<put-attribute name="htmlExtHeader" value="/tiles/dojoHtmlExtHeader.jsp" />
		<put-attribute name="body" value="/tiles/employee/edit.jsp" />
	</definition>

	<definition name="showEmployeePage" extends="baseLayoutWithMenu">
		<put-attribute name="body" value="/tiles/employee/view.jsp" />
	</definition>	
	
	<!--  Store tiles definition -->
	<definition name="listStoresPage" extends="baseLayoutWithMenu">
		<put-attribute name="body" value="/tiles/store/list.jsp" />
	</definition>
		
	<definition name="editStorePage" extends="baseLayoutWithMenu">
		<put-attribute name="body" value="/tiles/store/edit.jsp" />
	</definition>

	<definition name="showStorePage" extends="baseLayoutWithMenu">
		<put-attribute name="body" value="/tiles/store/view.jsp" />
	</definition>	
	
	<definition name="storeExtendedCRUD" template="/layouts/store/store_ext_crud.jsp" extends="baseLayoutWithMenu">
	  <put-attribute name="storeData" value="/tiles/store/storedata.jsp" />
	</definition>
	
	<definition name="editWeekdayGuestServ" extends="storeExtendedCRUD">
		<put-attribute name="storeExtDataBody" value="/tiles/store/weekdayguestserv_edit.jsp" />
	</definition>

	<definition name="showWeekdayGuestServ" extends="storeExtendedCRUD">
		<put-attribute name="storeExtDataBody" value="/tiles/store/weekdayguestserv_view.jsp" />
	</definition>

	<definition name="editOperationTimePage" extends="storeExtendedCRUD">
		<put-attribute name="storeExtDataBody" value="/tiles/store/operationtimes_edit.jsp" />
	</definition>

	<definition name="showOperationTimePage" extends="storeExtendedCRUD">
		<put-attribute name="storeExtDataBody" value="/tiles/store/operationtimes_view.jsp" />
	</definition>
	
	<definition name="editPositionNames" extends="storeExtendedCRUD">
		<put-attribute name="storeExtDataBody" value="/tiles/store/positionnames_edit.jsp" />
	</definition>

	<definition name="showPositionNames" extends="storeExtendedCRUD">
		<put-attribute name="storeExtDataBody" value="/tiles/store/positionnames_view.jsp" />
	</definition>	
	
	<definition name="editDaypartDefinition" extends="storeExtendedCRUD">
		<put-attribute name="storeExtDataBody" value="/tiles/store/daypartdefinition_edit.jsp" />
	</definition>

	<definition name="showDaypartDefinition" extends="storeExtendedCRUD">
		<put-attribute name="storeExtDataBody" value="/tiles/store/daypartdefinition_view.jsp" />
	</definition>		
	
	<definition name="editWeekendGuestServ" extends="storeExtendedCRUD">
		<put-attribute name="storeExtDataBody" value="/tiles/store/weekendguestserv_edit.jsp" />
	</definition>

	<definition name="showWeekendGuestServ" extends="storeExtendedCRUD">
		<put-attribute name="storeExtDataBody" value="/tiles/store/weekendguestserv_view.jsp" />
	</definition>
	
	<definition name="editVariableFlexible" extends="storeExtendedCRUD">
		<put-attribute name="storeExtDataBody" value="/tiles/store/variableflexible_edit.jsp" />
	</definition>

	<definition name="showVariableFlexible" extends="storeExtendedCRUD">
		<put-attribute name="storeExtDataBody" value="/tiles/store/variableflexible_view.jsp" />
	</definition>			

	<definition name="editVariableOpening" extends="storeExtendedCRUD">
		<put-attribute name="storeExtDataBody" value="/tiles/store/variableopening_edit.jsp" />
	</definition>

	<definition name="showVariableOpening" extends="storeExtendedCRUD">
		<put-attribute name="storeExtDataBody" value="/tiles/store/variableopening_view.jsp" />
	</definition>		
	
	<definition name="editFixedGuestServ" extends="storeExtendedCRUD">
		<put-attribute name="storeExtDataBody" value="/tiles/store/fixedguestserv_edit.jsp" />
	</definition>

	<definition name="showFixedGuestServ" extends="storeExtendedCRUD">
		<put-attribute name="storeExtDataBody" value="/tiles/store/fixedguestserv_view.jsp" />
	</definition>		

	<definition name="editFixedFlexible" extends="storeExtendedCRUD">
		<put-attribute name="storeExtDataBody" value="/tiles/store/fixedflexible_edit.jsp" />
	</definition>

	<definition name="showFixedFlexible" extends="storeExtendedCRUD">
		<put-attribute name="storeExtDataBody" value="/tiles/store/fixedflexible_view.jsp" />
	</definition>	

	<definition name="editMinimumStaffing" extends="storeExtendedCRUD">
		<put-attribute name="storeExtDataBody" value="/tiles/store/minimumstaffing_edit.jsp" />
	</definition>

	<definition name="showMinimumStaffing" extends="storeExtendedCRUD">
		<put-attribute name="storeExtDataBody" value="/tiles/store/minimumstaffing_view.jsp" />
	</definition>	
	
	<definition name="editFixedOpening" extends="storeExtendedCRUD">
		<put-attribute name="storeExtDataBody" value="/tiles/store/fixedopening_edit.jsp" />
	</definition>

	<definition name="showFixedOpening" extends="storeExtendedCRUD">
		<put-attribute name="storeExtDataBody" value="/tiles/store/fixedopening_view.jsp" />
	</definition>	
	
	<definition name="editFixedClosing" extends="storeExtendedCRUD">
		<put-attribute name="storeExtDataBody" value="/tiles/store/fixedclosing_edit.jsp" />
	</definition>

	<definition name="showFixedClosing" extends="storeExtendedCRUD">
		<put-attribute name="storeExtDataBody" value="/tiles/store/fixedclosing_view.jsp" />
	</definition>	

	<definition name="editFixedPostRush" extends="storeExtendedCRUD">
		<put-attribute name="storeExtDataBody" value="/tiles/store/fixedpostrush_edit.jsp" />
	</definition>

	<definition name="showFixedPostRush" extends="storeExtendedCRUD">
		<put-attribute name="storeExtDataBody" value="/tiles/store/fixedpostrush_view.jsp" />
	</definition>	

</tiles-definitions>